progtrack/__init__.py
progtrack/cli.py
progtrack-0.1.6.dist-info/METADATA
progtrack-0.1.6.dist-info/WHEEL
progtrack-0.1.6.dist-info/entry_points.txt
progtrack-0.1.6.dist-info/top_level.txt
progtrack-0.1.6.dist-info/RECORD
