Metadata-Version: 2.4
Name: progtrack
Version: 0.1.6
Summary: Track @progress comments across source code files
License: MIT
Project-URL: Source, https://github.com/shao-wang-me/progtrack
Requires-Dist: tabulate
